sqlalchemy_model_faker/__init__.py
sqlalchemy_model_faker-0.0.5.dist-info/LICENSE.txt
sqlalchemy_model_faker-0.0.5.dist-info/METADATA
sqlalchemy_model_faker-0.0.5.dist-info/WHEEL
sqlalchemy_model_faker-0.0.5.dist-info/top_level.txt
sqlalchemy_model_faker-0.0.5.dist-info/RECORD
