Metadata-Version: 2.1
Name: sqlalchemy_model_faker
Version: 0.0.5
Summary: Generate SQLAlchemy models with fake data
Home-page: https://github.com/rogervila/sqlalchemy_model_faker
Download-URL: https://github.com/rogervila/sqlalchemy_model_faker/archive/0.0.5.tar.gz
Author: Roger Vilà
Author-email: rogervila@me.com
License: MIT
Keywords: sqlalchemy fake model,sqlalchemy fake data
Classifier: Development Status :: 5 - Production/Stable
Classifier: Intended Audience :: Developers
Classifier: Topic :: Software Development :: Build Tools
Classifier: License :: OSI Approved :: MIT License
Classifier: Programming Language :: Python :: 3.9
License-File: LICENSE.txt
Requires-Dist: sqlalchemy >=1.4.32
Requires-Dist: Faker >=13.3.4
